aethergraph/__init__.py
aethergraph/__main__.py
aethergraph/api/v1/__init__.py
aethergraph/api/v1/agents.py
aethergraph/api/v1/apps.py
aethergraph/api/v1/artifacts.py
aethergraph/api/v1/channels.py
aethergraph/api/v1/deps.py
aethergraph/api/v1/graphs.py
aethergraph/api/v1/identity.py
aethergraph/api/v1/memory.py
aethergraph/api/v1/misc.py
aethergraph/api/v1/pagination.py
aethergraph/api/v1/runs.py
aethergraph/api/v1/schemas.py
aethergraph/api/v1/session.py
aethergraph/api/v1/stats.py
aethergraph/api/v1/viz.py
aethergraph/config/__init__.py
aethergraph/config/config.py
aethergraph/config/context.py
aethergraph/config/llm.py
aethergraph/config/loader.py
aethergraph/config/runtime.py
aethergraph/config/storage.py
aethergraph/contracts/__init__.py
aethergraph/contracts/errors/errors.py
aethergraph/contracts/services/__init__.py
aethergraph/contracts/services/artifacts.py
aethergraph/contracts/services/channel.py
aethergraph/contracts/services/continuations.py
aethergraph/contracts/services/eventbus.py
aethergraph/contracts/services/kv.py
aethergraph/contracts/services/llm.py
aethergraph/contracts/services/mcp.py
aethergraph/contracts/services/memory.py
aethergraph/contracts/services/metering.py
aethergraph/contracts/services/resume.py
aethergraph/contracts/services/runs.py
aethergraph/contracts/services/sessions.py
aethergraph/contracts/services/state_stores.py
aethergraph/contracts/services/viz.py
aethergraph/contracts/services/wakeup.py
aethergraph/contracts/storage/artifact_index.py
aethergraph/contracts/storage/artifact_store.py
aethergraph/contracts/storage/async_kv.py
aethergraph/contracts/storage/blob_store.py
aethergraph/contracts/storage/doc_store.py
aethergraph/contracts/storage/event_log.py
aethergraph/contracts/storage/vector_index.py
aethergraph/core/__init__.py
aethergraph/core/execution/base_scheduler.py
aethergraph/core/execution/forward_scheduler.py
aethergraph/core/execution/global_scheduler.py
aethergraph/core/execution/retry_policy.py
aethergraph-0.1.0a3.dist-info/licenses/LICENSE
aethergraph-0.1.0a3.dist-info/licenses/NOTICE
aethergraph-0.1.0a3.dist-info/METADATA
aethergraph-0.1.0a3.dist-info/WHEEL
aethergraph-0.1.0a3.dist-info/entry_points.txt
aethergraph-0.1.0a3.dist-info/top_level.txt
aethergraph-0.1.0a3.dist-info/RECORD
