Metadata-Version: 2.4
Name: aethergraph
Version: 0.1.0a3
Summary: Python-first agentic DAG execution framework
Author-email: Zhaocheng Liu <zhaocheng@aiperture.io>
License:                                 Apache License
Project-URL: Homepage, https://github.com/AIperture/aethergraph
Project-URL: Repository, https://github.com/AIperture/aethergraph
Project-URL: Documentation, https://aiperture.github.io/aethergraph-docs/
Project-URL: Issues, https://github.com/AIperture/aethergraph/issues
Keywords: agents,workflow,DAG,LLM,orchestration,research,aethergraph
Classifier: Development Status :: 3 - Alpha
Classifier: Intended Audience :: Science/Research
Classifier: Intended Audience :: Developers
Classifier: License :: OSI Approved :: Apache Software License
Classifier: Programming Language :: Python :: 3
Classifier: Programming Language :: Python :: 3 :: Only
Classifier: Programming Language :: Python :: 3.10
Classifier: Programming Language :: Python :: 3.11
Classifier: Programming Language :: Python :: 3.12
Classifier: Topic :: Scientific/Engineering
Classifier: Topic :: Software Development :: Libraries
Requires-Python: >=3.10
License-File: LICENSE
License-File: NOTICE
Requires-Dist: fastapi<1.0,>=0.110
Requires-Dist: uvicorn[standard]>=0.31
Requires-Dist: pydantic>=2.6
Requires-Dist: pydantic-settings>=2.2
Requires-Dist: numpy>=1.24
Requires-Dist: networkx>=3.1
Requires-Dist: python-multipart>=0.0.9
Requires-Dist: jsonschema>=4.18
Requires-Dist: httpx>=0.27
Requires-Dist: aiohttp>=3.9
Provides-Extra: slack
Requires-Dist: slack_sdk>=3.27.0; extra == "slack"
Requires-Dist: aiohttp>=3.9; extra == "slack"
Provides-Extra: telegram
Requires-Dist: aiohttp>=3.9; extra == "telegram"
Provides-Extra: webhook
Requires-Dist: aiohttp>=3.9; extra == "webhook"
Provides-Extra: discord
Requires-Dist: aiohttp>=3.9; extra == "discord"
Provides-Extra: channels
Requires-Dist: aethergraph[slack]; extra == "channels"
Requires-Dist: aethergraph[telegram]; extra == "channels"
Requires-Dist: aethergraph[webhook]; extra == "channels"
Provides-Extra: faiss
Requires-Dist: faiss-cpu>=1.7.4; extra == "faiss"
Provides-Extra: dev
Requires-Dist: ruff>=0.5; extra == "dev"
Requires-Dist: black>=24.1.0; extra == "dev"
Requires-Dist: mypy>=1.8.0; extra == "dev"
Requires-Dist: pytest>=8.0.0; extra == "dev"
Requires-Dist: pytest-asyncio>=0.23; extra == "dev"
Requires-Dist: types-requests>=2.31.0.10; extra == "dev"
Provides-Extra: docs
Requires-Dist: mkdocs>=1.5; extra == "docs"
Requires-Dist: mkdocs-material>=9.5; extra == "docs"
Requires-Dist: mkdocstrings[python]>=0.24; extra == "docs"
Provides-Extra: test
Requires-Dist: pytest>=8.0.0; extra == "test"
Requires-Dist: pytest-asyncio>=0.23; extra == "test"
Requires-Dist: coverage>=7.4; extra == "test"
Requires-Dist: trio; extra == "test"
Dynamic: license-file
